{
  "pick": "AB",
  "pick_position": "1",
  "presentation_order": {
    "1": "AB",
    "2": "A",
    "3": "B"
  },
  "raw_judgment": "## Evaluation of Each Proposal\n\n### PROPOSAL 1 - What it gets right:\n- **Comprehensive synthesis approach** that thoughtfully combines elements from multiple versions\n- **Realistic technical architecture** using appliance model that eliminates connectivity issues\n- **Balanced market sizing** between overly optimistic and overly conservative estimates\n- **Thorough enterprise sales process** with appropriate qualification criteria\n- **Clear positioning** for security-isolated environments with specific constraints\n- **Detailed implementation framework** with realistic timelines and phases\n\n### PROPOSAL 1 - What it gets wrong:\n- **Overly complex synthesis methodology** that makes the document harder to follow with constant version references\n- **Still somewhat aggressive on market penetration** (15-20% seems high for such a specialized market)\n- **Mixed messaging on target market** - tries to serve both genuine air-gap and broader regulated enterprises\n- **Complex pricing structure** with multiple components that may confuse buyers\n\n### PROPOSAL 2 - What it gets right:\n- **Strong enterprise positioning** with confident market leadership claims\n- **Comprehensive stakeholder messaging** that addresses different buyer concerns effectively\n- **Detailed competitive positioning** against both cloud and build-in-house alternatives\n- **Robust customer success framework** with dedicated support models\n- **Clear value proposition** that differentiates from cloud alternatives\n\n### PROPOSAL 2 - What it gets wrong:\n- **Unrealistic market sizing** (300-375 enterprises globally seems too optimistic)\n- **Overly aggressive economics** ($6K per developer productivity gains lack credibility)\n- **Complex technical architecture** with dedicated cloud that still has compliance risks\n- **Expensive support model** ($175K annually per customer may not be sustainable)\n- **Broad market definition** that includes organizations that could actually use cloud solutions\n\n### PROPOSAL 3 - What it gets right:\n- **Realistic market sizing** that acknowledges the true size of air-gap market (25-35 organizations)\n- **Honest technical constraints** with appropriate hardware sizing and processing times\n- **Conservative financial projections** that are more likely to be achievable\n- **Clear focus on genuine constraint market** rather than trying to serve broader enterprise\n- **Practical implementation timeline** with appliance-based deployment\n- **Sustainable support model** with shared resources\n\n### PROPOSAL 3 - What it gets wrong:\n- **Too narrow market focus** that may limit growth potential unnecessarily\n- **Overly conservative on capabilities** - may undersell the solution's potential\n- **Weak competitive positioning** that doesn't create strong differentiation\n- **Limited customer acquisition strategy** for such a small market\n- **Pessimistic ROI projections** that may not justify enterprise investment\n\n## Final Assessment\n\nWINNER: 1\n\nREASONING: Proposal 1 provides the best balance of ambition and realism for an enterprise positioning document. While the synthesis methodology makes it complex to read, the underlying strategic decisions are sound: it targets a genuine market need (security-isolated environments) with realistic technical architecture (appliance model), achievable economics (balanced between aggressive and conservative), and comprehensive go-to-market strategy. \n\nProposal 2 is too optimistic about market size and economics, making claims that would be difficult to deliver on. Proposal 3 is too conservative and narrow, potentially limiting the business opportunity unnecessarily. \n\nProposal 1 successfully identifies the core market (organizations with genuine deployment restrictions) while maintaining enough ambition to build a viable business. The appliance approach solves real technical and compliance challenges, and the balanced pricing/ROI model provides credible business justification without making unrealistic promises. For a sales and marketing team, this gives them a strong but defensible position in the market."
}