{
  "pass": 14,
  "winner": "A",
  "scores": {
    "A": 6,
    "B": 6,
    "AB": 6
  },
  "valid_judges": 3,
  "elapsed": 215.9,
  "judge_details": [
    {
      "ranking": [
        "B",
        "A",
        "AB"
      ],
      "order": {
        "1": "A",
        "2": "B",
        "3": "AB"
      }
    },
    {
      "ranking": [
        "AB",
        "B",
        "A"
      ],
      "order": {
        "1": "AB",
        "2": "A",
        "3": "B"
      }
    },
    {
      "ranking": [
        "A",
        "AB",
        "B"
      ],
      "order": {
        "1": "AB",
        "2": "B",
        "3": "A"
      }
    }
  ]
}